{
    "": 0,

    "EAR": 1,

    "MuyPicado": 2,

    "Smart_tiny22": 3,

    "aguspicle": 4,

    "ale": 5,

    "alemovies": 6,

    "antares": 7,

    "basic_lady56": 8,

    "black_rosa72": 9,

    "choy93": 10,

    "dead_squod78": 11,

    "dry_trabb61": 12,

    "early_miss61": 13,

    "evii_barboza ": 14,

    "famous_may99": 15,

    "famous_pott5": 16,

    "free_ann4": 17,

    "fresh_bart35": 18,

    "front_wegg95": 19,

    "funny_gills6": 20,

    "gg": 21,

    "glad_judge57": 22,

    "glad_pip58": 23,

    "good_emily98": 24,

    "green_phib5": 25,

    "guilled": 26,

    "h": 27,

    "heisenberga": 28,

    "high_agent59": 29,

    "huge_single2": 30,

    "human_phib76": 31,

    "j": 32,

    "jos\u00e9 mar\u00eda onega": 33,

    "juu": 34,

    "kz": 35,

    "late_ann11": 36,

    "legal_aunt4": 37,

    "lgimba": 38,

    "loving_ann76": 39,

    "low_sydney7": 40,

    "luciana_vietti": 41,

    "lucio lvp": 42,

    "mac33": 43,

    "manubahamonde": 44,

    "mari30": 45,

    "martin_nani": 46,

    "martinoliba": 47,

    "matiasm": 48,

    "mica123": 49,

    "negro74": 50,

    "nice_lady99": 51,

    "nice_may89": 52,

    "nickant": 53,

    "nicomateucci": 54,

    "old_biddy80": 55,

    "open_judge12": 56,

    "pablo": 57,

    "poor_pip9": 58,

    "pra3t0r5": 59,

    "ready_pip25": 60,

    "rich_berry6": 61,

    "rich_major34": 62,

    "rogimba": 63,

    "sabri": 64,

    "safe_miss57": 65,

    "short_lady15": 66,

    "short_pip18": 67,

    "silvia_hernandez": 68,

    "simple_may70": 69,

    "soft_tiny66": 70,

    "tall_emily4": 71,

    "tatog74": 72,

    "test_user": 73,

    "top_ann37": 74,

    "top_kenwigs4": 75,

    "viko": 76,

    "vitto": 77,

    "waitamomentic": 78,

    "wide": 79,

    "wide_judge32": 80
}